{"v":"5.7.4","fr":60,"ip":0,"op":301,"w":1080,"h":1080,"nm":"Waiting","ddd":0,"assets":[],"layers":[{"ddd":0,"ind":1,"ty":4,"nm":"Clock","sr":1,"ks":{"o":{"a":1,"k":[{"i":{"x":[0.667],"y":[1]},"o":{"x":[0.333],"y":[0]},"t":40,"s":[0]},{"i":{"x":[0.667],"y":[1]},"o":{"x":[0.333],"y":[0]},"t":60,"s":[80]},{"i":{"x":[0.667],"y":[1]},"o":{"x":[0.333],"y":[0]},"t":220,"s":[80]},{"t":240,"s":[0]}],"ix":11},"r":{"a":0,"k":0,"ix":10},"p":{"a":0,"k":[524,534,0],"ix":2,"l":2},"a":{"a":0,"k":[0,0,0],"ix":1,"l":2},"s":{"a":0,"k":[100,100,100],"ix":6,"l":2}},"ao":0,"shapes":[{"ty":"gr","it":[{"ind":0,"ty":"sh","ix":1,"ks":{"a":0,"k":{"i":[[0,-184],[0,0]],"o":[[0,184],[0,0]],"v":[[18,-268],[16,16]],"c":false},"ix":2},"nm":"Path 1","mn":"ADBE Vector Shape - Group","hd":false},{"ty":"st","c":{"a":0,"k":[0.094117654539,0.231372563979,0.090196078431,1],"ix":3},"o":{"a":0,"k":100,"ix":4},"w":{"a":0,"k":50,"ix":5},"lc":2,"lj":2,"bm":0,"nm":"Stroke 1","mn":"ADBE Vector Graphic - Stroke","hd":false},{"ty":"fl","c":{"a":0,"k":[0.725490196078,0.388266948625,0.284505956313,1],"ix":4},"o":{"a":0,"k":100,"ix":5},"r":1,"bm":0,"nm":"Fill 1","mn":"ADBE Vector Graphic - Fill","hd":false},{"ty":"tr","p":{"a":0,"k":[15.938,15.875],"ix":2},"a":{"a":0,"k":[15.938,15.875],"ix":1},"s":{"a":0,"k":[100,100],"ix":3},"r":{"a":1,"k":[{"i":{"x":[0.61],"y":[1]},"o":{"x":[0.39],"y":[0]},"t":40,"s":[0]},{"t":250,"s":[90]}],"ix":6},"o":{"a":0,"k":100,"ix":7},"sk":{"a":0,"k":0,"ix":4},"sa":{"a":0,"k":0,"ix":5},"nm":"Transform"}],"nm":"Shape 2","np":3,"cix":2,"bm":0,"ix":1,"mn":"ADBE Vector Group","hd":false},{"ty":"gr","it":[{"ind":0,"ty":"sh","ix":1,"ks":{"a":0,"k":{"i":[[0,-184],[0,0]],"o":[[0,184],[0,0]],"v":[[18,-372],[16,16]],"c":false},"ix":2},"nm":"Path 1","mn":"ADBE Vector Shape - Group","hd":false},{"ty":"st","c":{"a":0,"k":[0.094117654539,0.231372563979,0.090196078431,1],"ix":3},"o":{"a":0,"k":100,"ix":4},"w":{"a":0,"k":40,"ix":5},"lc":2,"lj":2,"bm":0,"nm":"Stroke 1","mn":"ADBE Vector Graphic - Stroke","hd":false},{"ty":"fl","c":{"a":0,"k":[0.725490196078,0.388266948625,0.284505956313,1],"ix":4},"o":{"a":0,"k":100,"ix":5},"r":1,"bm":0,"nm":"Fill 1","mn":"ADBE Vector Graphic - Fill","hd":false},{"ty":"tr","p":{"a":0,"k":[15.938,15.875],"ix":2},"a":{"a":0,"k":[15.938,15.875],"ix":1},"s":{"a":0,"k":[100,100],"ix":3},"r":{"a":1,"k":[{"i":{"x":[0.61],"y":[1]},"o":{"x":[0.39],"y":[0]},"t":40,"s":[0]},{"t":250,"s":[1080]}],"ix":6},"o":{"a":0,"k":100,"ix":7},"sk":{"a":0,"k":0,"ix":4},"sa":{"a":0,"k":0,"ix":5},"nm":"Transform"}],"nm":"Shape 1","np":3,"cix":2,"bm":0,"ix":2,"mn":"ADBE Vector Group","hd":false},{"ty":"gr","it":[{"ind":0,"ty":"sh","ix":1,"ks":{"a":0,"k":{"i":[[235.273,0],[0,-235.273],[-235.273,0],[0,235.273]],"o":[[-235.273,0],[0,235.273],[235.273,0],[0,-235.273]],"v":[[0,-426],[-426,0],[0,426],[426,0]],"c":true},"ix":2},"nm":"Path 1","mn":"ADBE Vector Shape - Group","hd":false},{"ty":"st","c":{"a":0,"k":[0.09562330059,0.23137254902,0.088919635848,1],"ix":3},"o":{"a":0,"k":100,"ix":4},"w":{"a":0,"k":30,"ix":5},"lc":2,"lj":1,"ml":4,"bm":0,"nm":"Stroke 1","mn":"ADBE Vector Graphic - Stroke","hd":false},{"ty":"tr","p":{"a":0,"k":[16,6],"ix":2},"a":{"a":0,"k":[0,0],"ix":1},"s":{"a":0,"k":[100,100],"ix":3},"r":{"a":0,"k":0,"ix":6},"o":{"a":0,"k":100,"ix":7},"sk":{"a":0,"k":0,"ix":4},"sa":{"a":0,"k":0,"ix":5},"nm":"Transform"}],"nm":"Ellipse 1","np":3,"cix":2,"bm":0,"ix":3,"mn":"ADBE Vector Group","hd":false}],"ip":0,"op":600,"st":0,"bm":0},{"ddd":0,"ind":2,"ty":4,"nm":"BODY","sr":1,"ks":{"o":{"a":0,"k":100,"ix":11},"r":{"a":0,"k":0,"ix":10},"p":{"s":true,"x":{"a":0,"k":540,"ix":3},"y":{"a":1,"k":[{"i":{"x":[0.49],"y":[1]},"o":{"x":[0.51],"y":[0]},"t":20,"s":[816.5]},{"i":{"x":[0.49],"y":[1]},"o":{"x":[0.51],"y":[0]},"t":30,"s":[766]},{"i":{"x":[0.49],"y":[1]},"o":{"x":[0.51],"y":[0]},"t":40,"s":[816.5]},{"i":{"x":[0.49],"y":[1]},"o":{"x":[0.51],"y":[0]},"t":230,"s":[816.5]},{"i":{"x":[0.49],"y":[1]},"o":{"x":[0.51],"y":[0]},"t":240,"s":[766]},{"t":250,"s":[816.5]}],"ix":4}},"a":{"a":0,"k":[513.5,887.667,0],"ix":1,"l":2},"s":{"a":0,"k":[84.462,84.462,100],"ix":6,"l":2}},"ao":0,"shapes":[{"ty":"gr","it":[{"ind":0,"ty":"sh","ix":1,"ks":{"a":1,"k":[{"t":20,"s":[{"i":[[-18.128,65.569],[0,23.593],[76.307,0],[0,-84.591],[-8.597,-31.095],[0,-212.589],[0,0],[0,0],[0,0],[0,0]],"o":[[8.597,-31.095],[0,-84.591],[-76.307,0],[0,23.593],[18.112,65.511],[0,0],[0,0],[0,0],[0,0],[0,-212.707]],"v":[[124.756,-80.083],[138.167,-171.834],[0,-325],[-138.167,-171.834],[-124.756,-80.083],[-148.5,141],[-148.5,325],[2.027,325],[148.5,325],[148.5,141]],"c":true}],"h":1},{"i":{"x":0.568,"y":1},"o":{"x":0.881,"y":0},"t":40,"s":[{"i":[[-18.128,65.569],[0,23.593],[76.307,0],[0,-84.591],[-8.597,-31.095],[-23.176,-107.849],[143.941,23.088],[-50.35,-1.183],[0,0],[0,0]],"o":[[8.597,-31.095],[0,-84.591],[-76.307,0],[0,23.593],[18.112,65.511],[0,0],[-143.941,-23.088],[50.35,1.183],[0,0],[0,-212.707]],"v":[[124.756,-80.083],[138.167,-171.834],[0,-325],[-138.167,-171.834],[-124.756,-80.083],[-148.5,141],[-240.85,237.386],[-115.186,325.311],[148.5,325],[148.5,141]],"c":true}]},{"i":{"x":0.568,"y":1},"o":{"x":0.881,"y":0},"t":60,"s":[{"i":[[-18.128,65.569],[0,23.593],[76.307,0],[0,-84.591],[-8.597,-31.095],[0,-212.589],[110.636,-26.604],[-72.717,59.138],[-95.221,-29.007],[67.99,65.226]],"o":[[8.597,-31.095],[0,-84.591],[-76.307,0],[0,23.593],[18.112,65.511],[0,0],[-140.391,18.322],[91.493,-30.507],[51.827,15.788],[-67.99,-65.226]],"v":[[214.738,-139.282],[228.148,-231.033],[89.982,-384.199],[-48.185,-231.033],[-34.774,-139.282],[-148.5,141],[-242.033,311.924],[-135.3,318.212],[127.188,333.287],[148.5,141]],"c":true}]},{"i":{"x":0.568,"y":1},"o":{"x":0.881,"y":0},"t":80,"s":[{"i":[[-18.128,65.569],[0,23.593],[76.307,0],[0,-84.591],[-8.597,-31.095],[-75.271,-178.887],[143.938,23.084],[-50.351,-1.178],[-161.521,-51.503],[51.414,71.145]],"o":[[8.597,-31.095],[0,-84.591],[-76.307,0],[0,23.593],[18.112,65.511],[0,0],[-143.94,-23.084],[50.353,1.18],[66.433,21.183],[-51.414,-71.145]],"v":[[123.579,-132.183],[136.99,-223.934],[-1.177,-377.099],[-139.344,-223.934],[-125.932,-132.183],[-148.5,141],[-240.85,237.392],[-115.188,325.31],[124.818,332.104],[148.5,141]],"c":true}]},{"i":{"x":0.568,"y":1},"o":{"x":0.881,"y":0},"t":100,"s":[{"i":[[-18.128,65.569],[0,23.593],[76.307,0],[0,-84.591],[-8.597,-31.095],[0,-212.589],[110.636,-26.604],[-72.717,59.138],[-95.221,-29.007],[67.99,65.226]],"o":[[8.597,-31.095],[0,-84.591],[-76.307,0],[0,23.593],[18.112,65.511],[0,0],[-140.391,18.322],[91.493,-30.507],[51.827,15.788],[-67.99,-65.226]],"v":[[214.738,-139.281],[228.148,-231.033],[89.982,-384.199],[-48.185,-231.033],[-34.774,-139.281],[-148.5,141],[-242.033,311.924],[-135.3,318.212],[127.188,333.287],[148.5,141]],"c":true}]},{"i":{"x":0.568,"y":1},"o":{"x":0.881,"y":0},"t":120,"s":[{"i":[[-18.128,65.569],[0,23.593],[76.307,0],[0,-84.591],[-8.597,-31.095],[-75.271,-178.887],[143.938,23.084],[-50.351,-1.178],[-161.521,-51.503],[51.414,71.145]],"o":[[8.597,-31.095],[0,-84.591],[-76.307,0],[0,23.593],[18.112,65.511],[0,0],[-143.94,-23.084],[50.353,1.18],[66.433,21.183],[-51.414,-71.145]],"v":[[123.579,-132.183],[136.99,-223.934],[-1.177,-377.099],[-139.344,-223.934],[-125.932,-132.183],[-148.5,141],[-240.85,237.392],[-115.188,325.31],[124.818,332.104],[148.5,141]],"c":true}]},{"i":{"x":0.568,"y":1},"o":{"x":0.881,"y":0},"t":140,"s":[{"i":[[-18.128,65.569],[0,23.593],[76.307,0],[0,-84.591],[-8.597,-31.095],[0,-212.589],[110.636,-26.604],[-72.717,59.138],[-95.221,-29.007],[67.99,65.226]],"o":[[8.597,-31.095],[0,-84.591],[-76.307,0],[0,23.593],[18.112,65.511],[0,0],[-140.391,18.322],[91.493,-30.507],[51.827,15.788],[-67.99,-65.226]],"v":[[214.738,-139.281],[228.148,-231.033],[89.982,-384.199],[-48.185,-231.033],[-34.774,-139.281],[-148.5,141],[-242.033,311.924],[-135.3,318.212],[127.188,333.287],[148.5,141]],"c":true}]},{"i":{"x":0.568,"y":1},"o":{"x":0.881,"y":0},"t":160,"s":[{"i":[[-18.128,65.569],[0,23.593],[76.307,0],[0,-84.591],[-8.597,-31.095],[-75.271,-178.887],[143.938,23.084],[-50.351,-1.178],[-161.521,-51.503],[51.414,71.145]],"o":[[8.597,-31.095],[0,-84.591],[-76.307,0],[0,23.593],[18.112,65.511],[0,0],[-143.94,-23.084],[50.353,1.18],[66.433,21.183],[-51.414,-71.145]],"v":[[123.579,-132.183],[136.99,-223.934],[-1.177,-377.099],[-139.344,-223.934],[-125.932,-132.183],[-148.5,141],[-240.85,237.392],[-115.188,325.31],[124.818,332.104],[148.5,141]],"c":true}]},{"i":{"x":0.568,"y":1},"o":{"x":0.881,"y":0},"t":180,"s":[{"i":[[-18.128,65.569],[0,23.593],[76.307,0],[0,-84.591],[-8.597,-31.095],[0,-212.589],[110.636,-26.604],[-72.717,59.138],[-95.221,-29.007],[67.99,65.226]],"o":[[8.597,-31.095],[0,-84.591],[-76.307,0],[0,23.593],[18.112,65.511],[0,0],[-140.391,18.322],[91.493,-30.507],[51.827,15.788],[-67.99,-65.226]],"v":[[214.738,-139.281],[228.148,-231.033],[89.982,-384.199],[-48.185,-231.033],[-34.774,-139.281],[-148.5,141],[-242.033,311.924],[-135.3,318.212],[127.188,333.287],[148.5,141]],"c":true}]},{"i":{"x":0.568,"y":1},"o":{"x":0.881,"y":0},"t":200,"s":[{"i":[[-18.128,65.569],[0,23.593],[76.307,0],[0,-84.591],[-8.597,-31.095],[-75.271,-178.887],[143.938,23.084],[-50.351,-1.178],[-161.521,-51.503],[51.414,71.145]],"o":[[8.597,-31.095],[0,-84.591],[-76.307,0],[0,23.593],[18.112,65.511],[0,0],[-143.94,-23.084],[50.353,1.18],[66.433,21.183],[-51.414,-71.145]],"v":[[123.579,-132.183],[136.99,-223.934],[-1.177,-377.099],[-139.344,-223.934],[-125.932,-132.183],[-148.5,141],[-240.85,237.392],[-115.188,325.31],[124.818,332.104],[148.5,141]],"c":true}]},{"i":{"x":1,"y":1},"o":{"x":1,"y":0},"t":220,"s":[{"i":[[-18.128,65.569],[0,23.593],[76.307,0],[0,-84.591],[-8.597,-31.095],[0,-212.589],[110.636,-26.604],[-72.717,59.138],[-95.221,-29.007],[67.99,65.226]],"o":[[8.597,-31.095],[0,-84.591],[-76.307,0],[0,23.593],[18.112,65.511],[0,0],[-140.391,18.322],[91.493,-30.507],[51.827,15.788],[-67.99,-65.226]],"v":[[214.738,-139.281],[228.148,-231.033],[89.982,-384.199],[-48.185,-231.033],[-34.774,-139.281],[-148.5,141],[-242.033,311.924],[-135.3,318.212],[127.188,333.287],[148.5,141]],"c":true}]},{"i":{"x":0.195,"y":1},"o":{"x":0.167,"y":0.541},"t":230,"s":[{"i":[[-18.128,65.569],[0,23.593],[76.307,0],[0,-84.591],[-8.597,-31.095],[69.967,-154.548],[-8.969,-75.129],[-99.127,3.828],[-98.51,14.295],[32.711,88.357]],"o":[[8.597,-31.095],[0,-84.591],[-76.307,0],[0,23.593],[18.112,65.511],[-32.648,72.115],[21.814,65.763],[79.653,-11.563],[69.351,-10.063],[-44.31,-119.688]],"v":[[214.737,-139.282],[228.148,-231.033],[89.982,-384.199],[-48.185,-231.033],[-34.774,-139.282],[-162.708,61.674],[-194.674,257.461],[-44.134,299.268],[124.82,303.688],[186.387,61.674]],"c":true}]},{"t":250,"s":[{"i":[[-18.128,65.569],[0,23.593],[76.307,0],[0,-84.591],[-8.597,-31.095],[0,-212.589],[0,0],[0,0],[0,0],[0,0]],"o":[[8.597,-31.095],[0,-84.591],[-76.307,0],[0,23.593],[18.112,65.511],[0,0],[0,0],[0,0],[0,0],[0,-212.707]],"v":[[124.756,-80.083],[138.167,-171.834],[0,-325],[-138.167,-171.834],[-124.756,-80.083],[-148.5,141],[-148.5,325],[2.027,325],[148.5,325],[148.5,141]],"c":true}]}],"ix":2},"nm":"Path 1","mn":"ADBE Vector Shape - Group","hd":false},{"ty":"fl","c":{"a":0,"k":[0,0.407843167174,0.215686289469,1],"ix":4},"o":{"a":0,"k":100,"ix":5},"r":1,"bm":0,"nm":"Fill 1","mn":"ADBE Vector Graphic - Fill","hd":false},{"ty":"tr","p":{"a":0,"k":[513.5,560.299],"ix":2},"a":{"a":0,"k":[0,0],"ix":1},"s":{"a":0,"k":[100,100],"ix":3},"r":{"a":0,"k":0,"ix":6},"o":{"a":0,"k":100,"ix":7},"sk":{"a":0,"k":0,"ix":4},"sa":{"a":0,"k":0,"ix":5},"nm":"Transform"}],"nm":"Group 1","np":2,"cix":2,"bm":0,"ix":1,"mn":"ADBE Vector Group","hd":false}],"ip":0,"op":600,"st":0,"bm":0}],"markers":[]}